{"id":14660,"slug":"light-blast","title":"Light Blast","title_hi":null,"year":"1985","type":"movie","plot":"A crazed physician invents a death ray and threatens to destroy San Francisco unless he is paid $10 million.","plot_hi":null,"runtime":"86 min","rated":"R","language":null,"country":"Italy","box_office":null,"awards":null,"imdb_id":null,"imdb_rating":"5.1","status":"published","image_url":"att0088940z.jpg","date_created":"2021-01-31T13:46:20.124Z","ratings":[{"source":"Internet Movie Database","value":"5.1/10"}],"genres":[{"id":1,"name":"Action","slug":"action"},{"id":21,"name":"Sci-Fi","slug":"sci-fi"},{"id":25,"name":"Thriller","slug":"thriller"}],"cast":[{"id":10627,"name":"Erik Estrada","slug":"erik-estrada"},{"id":21681,"name":"Ennio Girolami","slug":"ennio-girolami"},{"id":21682,"name":"Michael Pritchard","slug":"michael-pritchard"},{"id":21683,"name":"Peggy Rowe","slug":"peggy-rowe"}],"directors":[{"id":9548,"name":"Enzo G. Castellari","slug":"enzo-g.-castellari"}],"writers":[{"id":9548,"name":"Enzo G. Castellari","slug":"enzo-g.-castellari"},{"id":14180,"name":"Tito Carpi","slug":"tito-carpi"}],"recommendations":[{"id":39642,"slug":"chips","title":"CHiPs","title_hi":null,"year":"1977–1983","type":"series","imdb_rating":"6.4","image_url":"att0075488z.jpg"},{"id":39223,"slug":"angel-eyes","title":"Angel Eyes","title_hi":null,"year":"1993","type":"movie","imdb_rating":"4.2","image_url":"att0106278z.jpg"},{"id":33260,"slug":"do-or-die","title":"Do or Die","title_hi":null,"year":"1991","type":"movie","imdb_rating":"4","image_url":"att0101744z.jpg"},{"id":32793,"slug":"guns","title":"Guns","title_hi":null,"year":"1990","type":"movie","imdb_rating":"4.2","image_url":"att0099720z.jpg"},{"id":23932,"slug":"chupacabra-vs.-the-alamo","title":"Chupacabra vs. the Alamo","title_hi":null,"year":"2013","type":"movie","imdb_rating":"3.1","image_url":"att2247748z.jpg"},{"id":21521,"slug":"killer-crocodile-2","title":"Killer Crocodile 2","title_hi":null,"year":"1990","type":"movie","imdb_rating":"4.2","image_url":"att0099934z.jpg"},{"id":17671,"slug":"visions","title":"Visions","title_hi":null,"year":"1998","type":"movie","imdb_rating":"3.4","image_url":"att0183981z.jpg"},{"id":17082,"slug":"alien-seed","title":"Alien Seed","title_hi":null,"year":"1989","type":"movie","imdb_rating":"2.7","image_url":"att0096784z.jpg"},{"id":16874,"slug":"twisted-justice","title":"Twisted Justice","title_hi":null,"year":"1990","type":"movie","imdb_rating":"3.7","image_url":"att0100826z.jpg"},{"id":9498,"slug":"cool-cat-saves-the-kids","title":"Cool Cat Saves the Kids","title_hi":null,"year":"2015","type":"movie","imdb_rating":"4.7","image_url":"att2974050z.jpg"},{"id":1209,"slug":"the-cross-and-the-switchblade","title":"The Cross and the Switchblade","title_hi":null,"year":"1970","type":"movie","imdb_rating":"6.2","image_url":"att0068428z.jpg"}],"updatedAt":"2026-03-24T12:56:59.933Z"}