{"id":17994,"slug":"servant","title":"Servant","title_hi":null,"year":"2019–","type":"series","plot":"A Philadelphia couple is in mourning after an unspeakable tragedy creates a rift in their marriage and opens the door for a mysterious force to enter their home.","plot_hi":null,"runtime":"30 min","rated":"TV-MA","language":null,"country":"USA","box_office":null,"awards":"1 nomination.","imdb_id":null,"imdb_rating":"7.6","status":"published","image_url":"att8068860z.jpg","date_created":"2021-03-07T07:45:42.700Z","ratings":[{"source":"Internet Movie Database","value":"7.6/10"}],"genres":[{"id":9,"name":"Drama","slug":"drama"},{"id":15,"name":"Horror","slug":"horror"},{"id":25,"name":"Thriller","slug":"thriller"}],"cast":[{"id":13589,"name":"Lauren Ambrose","slug":"lauren-ambrose"},{"id":1112,"name":"Toby Kebbell","slug":"toby-kebbell"},{"id":34524,"name":"Nell Tiger Free","slug":"nell-tiger-free"},{"id":214,"name":"Rupert Grint","slug":"rupert-grint"}],"directors":[],"writers":[],"recommendations":[{"id":40594,"slug":"daniel","title":"Daniel","title_hi":null,"year":"2019","type":"movie","imdb_rating":"8","image_url":"att9179230z.jpg"},{"id":36397,"slug":"the-east","title":"The East","title_hi":null,"year":"2013","type":"movie","imdb_rating":"6.8","image_url":"att1869716z.jpg"},{"id":36248,"slug":"too-old-to-die-young","title":"Too Old to Die Young","title_hi":null,"year":"2019","type":"series","imdb_rating":"7.4","image_url":"att6517320z.jpg"},{"id":31847,"slug":"the-hurricane-heist","title":"The Hurricane Heist","title_hi":null,"year":"2018","type":"movie","imdb_rating":"5.1","image_url":"att5360952z.jpg"},{"id":31582,"slug":"destroyer","title":"Destroyer","title_hi":null,"year":"2018","type":"movie","imdb_rating":"6.2","image_url":"att7137380z.jpg"},{"id":23206,"slug":"the-darkness","title":"The Darkness","title_hi":null,"year":"2007","type":"game","imdb_rating":"8.5","image_url":"att0937352z.jpg"},{"id":19752,"slug":"wilderness","title":"Wilderness","title_hi":null,"year":"2006","type":"movie","imdb_rating":"6.1","image_url":"att0465670z.jpg"},{"id":10163,"slug":"bloodshot","title":"Bloodshot","title_hi":null,"year":"2020","type":"movie","imdb_rating":"5.7","image_url":"att1634106z.jpg"},{"id":10027,"slug":"postman-pat-the-movie","title":"Postman Pat: The Movie","title_hi":null,"year":"2014","type":"movie","imdb_rating":"4.6","image_url":"att2062622z.jpg"},{"id":9507,"slug":"driving-lessons","title":"Driving Lessons","title_hi":null,"year":"2006","type":"movie","imdb_rating":"6.7","image_url":"att0446687z.jpg"},{"id":4578,"slug":"psycho-beach-party","title":"Psycho Beach Party","title_hi":null,"year":"2000","type":"movie","imdb_rating":"6.2","image_url":"att0206226z.jpg"},{"id":159,"slug":"six-feet-under","title":"Six Feet Under","title_hi":null,"year":"2001–2005","type":"series","imdb_rating":"8.7","image_url":"att0248654z.jpg"}],"updatedAt":"2026-03-24T12:54:17.967Z"}