{"id":2389,"slug":"buffalo-66","title":"Buffalo '66","title_hi":null,"year":"1998","type":"movie","plot":"After being released from prison, Billy is set to visit his parents with his wife, whom he does not actually have. This provokes Billy to act out, as he kidnaps a girl and forces her to act as his wife for the visit.","plot_hi":null,"runtime":"110 min","rated":"R","language":null,"country":"USA, Canada","box_office":"$2,365,931","awards":"6 wins & 11 nominations.","imdb_id":null,"imdb_rating":"7.5","status":"published","image_url":"att0118789z.jpg","date_created":"2020-09-24T17:17:16.320Z","ratings":[{"source":"Internet Movie Database","value":"7.5/10"},{"source":"Rotten Tomatoes","value":"76%"},{"source":"Metacritic","value":"68/100"}],"genres":[{"id":6,"name":"Comedy","slug":"comedy"},{"id":9,"name":"Drama","slug":"drama"},{"id":20,"name":"Romance","slug":"romance"}],"cast":[{"id":15388,"name":"Vincent Gallo","slug":"vincent-gallo"},{"id":25168,"name":"Christina Ricci","slug":"christina-ricci"},{"id":11969,"name":"Ben Gazzara","slug":"ben-gazzara"},{"id":1677,"name":"Mickey Rourke","slug":"mickey-rourke"}],"directors":[{"id":15388,"name":"Vincent Gallo","slug":"vincent-gallo"}],"writers":[{"id":15388,"name":"Vincent Gallo","slug":"vincent-gallo"},{"id":55573,"name":"Alison Bagnall","slug":"alison-bagnall"}],"recommendations":[{"id":39772,"slug":"black-snake-moan","title":"Black Snake Moan","title_hi":null,"year":"2006","type":"movie","imdb_rating":"6.9","image_url":"att0462200z.jpg"},{"id":25949,"slug":"passion-play","title":"Passion Play","title_hi":null,"year":"2010","type":"movie","imdb_rating":"4.6","image_url":"att1396221z.jpg"},{"id":25042,"slug":"the-thomas-crown-affair","title":"The Thomas Crown Affair","title_hi":null,"year":"1999","type":"movie","imdb_rating":"6.8","image_url":"att0155267z.jpg"},{"id":24837,"slug":"immortals","title":"Immortals","title_hi":null,"year":"2011","type":"movie","imdb_rating":"6","image_url":"att1253864z.jpg"},{"id":18490,"slug":"nightmare-cinema","title":"Nightmare Cinema","title_hi":null,"year":"2018","type":"movie","imdb_rating":"5.5","image_url":"att7349910z.jpg"},{"id":18094,"slug":"angel-heart","title":"Angel Heart","title_hi":null,"year":"1987","type":"movie","imdb_rating":"7.3","image_url":"att0092563z.jpg"},{"id":12707,"slug":"weaponized","title":"WEAPONiZED","title_hi":null,"year":"2016","type":"movie","imdb_rating":"4.2","image_url":"att4776564z.jpg"},{"id":4777,"slug":"pumpkin","title":"Pumpkin","title_hi":null,"year":"2002","type":"movie","imdb_rating":"6.1","image_url":"att0265591z.jpg"},{"id":4321,"slug":"diner","title":"Diner","title_hi":null,"year":"1982","type":"movie","imdb_rating":"7.1","image_url":"att0083833z.jpg"},{"id":3593,"slug":"ashby","title":"Ashby","title_hi":null,"year":"2015","type":"movie","imdb_rating":"6.4","image_url":"att3774466z.jpg"},{"id":2759,"slug":"spun","title":"Spun","title_hi":null,"year":"2002","type":"movie","imdb_rating":"6.8","image_url":"att0283003z.jpg"},{"id":584,"slug":"now-and-then","title":"Now and Then","title_hi":null,"year":"1995","type":"movie","imdb_rating":"6.8","image_url":"att0114011z.jpg"}],"updatedAt":"2026-03-24T13:06:55.163Z"}