{"id":30149,"slug":"one-hour-with-you","title":"One Hour with You","title_hi":null,"year":"1932","type":"movie","plot":"An unhappily married couple try to come between a happy one.","plot_hi":null,"runtime":"78 min","rated":"Passed","language":null,"country":"USA","box_office":null,"awards":null,"imdb_id":null,"imdb_rating":"7.2","status":"published","image_url":"att0023303z.jpg","date_created":"2021-07-13T21:17:02.840Z","ratings":[{"source":"Internet Movie Database","value":"7.2/10"},{"source":"Rotten Tomatoes","value":"83%"}],"genres":[{"id":6,"name":"Comedy","slug":"comedy"},{"id":17,"name":"Musical","slug":"musical"},{"id":20,"name":"Romance","slug":"romance"}],"cast":[{"id":69947,"name":"Maurice Chevalier","slug":"maurice-chevalier"},{"id":60962,"name":"Jeanette MacDonald","slug":"jeanette-macdonald"},{"id":73906,"name":"Lili Damita","slug":"lili-damita"},{"id":57256,"name":"Genevieve Tobin","slug":"genevieve-tobin"}],"directors":[{"id":28318,"name":"George Cukor","slug":"george-cukor"},{"id":62496,"name":"Ernst Lubitsch","slug":"ernst-lubitsch"}],"writers":[{"id":61439,"name":"Samson Raphaelson","slug":"samson-raphaelson"},{"id":73907,"name":"Lothar Schmidt","slug":"lothar-schmidt"},{"id":73908,"name":"Léopold Marchand","slug":"leopold-marchand"}],"recommendations":[{"id":30999,"slug":"a-breath-of-scandal","title":"A Breath of Scandal","title_hi":null,"year":"1960","type":"movie","imdb_rating":"5.6","image_url":"att0053675z.jpg"},{"id":30462,"slug":"love-me-tonight","title":"Love Me Tonight","title_hi":null,"year":"1932","type":"movie","imdb_rating":"7.6","image_url":"att0023158z.jpg"},{"id":29290,"slug":"naughty-marietta","title":"Naughty Marietta","title_hi":null,"year":"1935","type":"movie","imdb_rating":"6.7","image_url":"att0026768z.jpg"},{"id":29105,"slug":"smilin-through","title":"Smilin' Through","title_hi":null,"year":"1941","type":"movie","imdb_rating":"6.6","image_url":"att0034203z.jpg"},{"id":28720,"slug":"fanny","title":"Fanny","title_hi":null,"year":"1961","type":"movie","imdb_rating":"7","image_url":"att0054866z.jpg"},{"id":28687,"slug":"jessica","title":"Jessica","title_hi":null,"year":"1962","type":"movie","imdb_rating":"5.6","image_url":"att0056117z.jpg"},{"id":26545,"slug":"the-petrified-forest","title":"The Petrified Forest","title_hi":null,"year":"1936","type":"movie","imdb_rating":"7.5","image_url":"att0028096z.jpg"},{"id":9617,"slug":"can-can","title":"Can-Can","title_hi":null,"year":"1960","type":"movie","imdb_rating":"6.4","image_url":"att0053690z.jpg"},{"id":9612,"slug":"the-merry-widow","title":"The Merry Widow","title_hi":null,"year":"1934","type":"movie","imdb_rating":"7.2","image_url":"att0025493z.jpg"},{"id":4706,"slug":"love-in-the-afternoon","title":"Love in the Afternoon","title_hi":null,"year":"1957","type":"movie","imdb_rating":"7.2","image_url":"att0050658z.jpg"},{"id":4126,"slug":"gigi","title":"Gigi","title_hi":null,"year":"1958","type":"movie","imdb_rating":"6.7","image_url":"att0051658z.jpg"}],"updatedAt":"2026-03-24T12:44:27.793Z"}