{"id":30438,"slug":"one-two-many","title":"One, Two, Many","title_hi":null,"year":"2008","type":"movie","plot":"A modern-day romance that follows one man's quest to find the girl of his dreams. A girl who can agree that three is company.","plot_hi":null,"runtime":"88 min","rated":"R","language":null,"country":"USA","box_office":null,"awards":null,"imdb_id":null,"imdb_rating":"3.5","status":"published","image_url":"att0882755z.jpg","date_created":"2021-07-16T21:31:11.432Z","ratings":[{"source":"Internet Movie Database","value":"3.5/10"}],"genres":[{"id":6,"name":"Comedy","slug":"comedy"},{"id":20,"name":"Romance","slug":"romance"}],"cast":[{"id":13663,"name":"John Melendez","slug":"john-melendez"},{"id":74704,"name":"Bellamy Young","slug":"bellamy-young"},{"id":74705,"name":"Jeffrey Ross","slug":"jeffrey-ross"},{"id":7408,"name":"Hudson Leick","slug":"hudson-leick"}],"directors":[{"id":42811,"name":"Michael DeLorenzo","slug":"michael-delorenzo"}],"writers":[{"id":13663,"name":"John Melendez","slug":"john-melendez"}],"recommendations":[{"id":38224,"slug":"the-night-stalker","title":"The Night Stalker","title_hi":null,"year":"2016","type":"movie","imdb_rating":"5.9","image_url":"att1821657z.jpg"},{"id":27592,"slug":"cold-heart","title":"Cold Heart","title_hi":null,"year":"2001","type":"movie","imdb_rating":"5.4","image_url":"att0276868z.jpg"},{"id":15266,"slug":"tripping-the-rift-the-movie","title":"Tripping the Rift: The Movie","title_hi":null,"year":"2008","type":"movie","imdb_rating":"5.4","image_url":"att1212448z.jpg"},{"id":12739,"slug":"tripping-the-rift","title":"Tripping the Rift","title_hi":null,"year":"2004–2007","type":"series","imdb_rating":"6.7","image_url":"att0315081z.jpg"},{"id":11423,"slug":"knight-rider-2010","title":"Knight Rider 2010","title_hi":null,"year":"1994","type":"movie","imdb_rating":"3.2","image_url":"att0110273z.jpg"},{"id":7506,"slug":"love-debt","title":"Love & Debt","title_hi":null,"year":"2019","type":"movie","imdb_rating":"4.7","image_url":"att3221910z.jpg"},{"id":6710,"slug":"historical-roasts","title":"Historical Roasts","title_hi":null,"year":"2019–","type":"series","imdb_rating":"5.3","image_url":"att9169602z.jpg"}],"updatedAt":"2026-03-24T12:44:13.745Z"}