{"id":32779,"slug":"ren","title":"Ren","title_hi":null,"year":"2016–","type":"series","plot":"When Ren is marked by a powerful ancient spirit she is forced to leave behind the family she has spent her whole life protecting and journey across the land to find the real meaning behind the mark she bears.","plot_hi":null,"runtime":"10 min","rated":null,"language":null,"country":"UK","box_office":null,"awards":"4 wins & 17 nominations.","imdb_id":null,"imdb_rating":"7","status":"published","image_url":"att4229228z.jpg","date_created":"2021-08-10T07:01:10.522Z","ratings":[{"source":"Internet Movie Database","value":"7.0/10"}],"genres":[{"id":1,"name":"Action","slug":"action"},{"id":3,"name":"Adventure","slug":"adventure"},{"id":9,"name":"Drama","slug":"drama"},{"id":11,"name":"Fantasy","slug":"fantasy"}],"cast":[{"id":6216,"name":"Sophie Skelton","slug":"sophie-skelton"},{"id":79778,"name":"Duran Fulton Brown","slug":"duran-fulton-brown"},{"id":79779,"name":"Nick Cornwall","slug":"nick-cornwall"},{"id":79780,"name":"James Malpas","slug":"james-malpas"}],"directors":[{"id":5,"name":"N/A","slug":"na"}],"writers":[{"id":5,"name":"N/A","slug":"na"}],"recommendations":[{"id":32388,"slug":"211","title":"211","title_hi":null,"year":"2018","type":"movie","imdb_rating":"4.4","image_url":"att4976192z.jpg"},{"id":24709,"slug":"outlander","title":"Outlander","title_hi":null,"year":"2014–","type":"series","imdb_rating":"8.4","image_url":"att3006802z.jpg"},{"id":11177,"slug":"day-of-the-dead-bloodline","title":"Day of the Dead: Bloodline","title_hi":null,"year":"2017","type":"movie","imdb_rating":"3.4","image_url":"att3053228z.jpg"},{"id":41309,"slug":"the-united-states-of-leland","title":"The United States of Leland","title_hi":null,"year":"2003","type":"movie","imdb_rating":"7.1","image_url":"att0301976z.jpg"},{"id":41297,"slug":"matt-houston","title":"Matt Houston","title_hi":null,"year":"1982–1985","type":"series","imdb_rating":"6.7","image_url":"att0083447z.jpg"},{"id":41287,"slug":"xxx-uncensored","title":"XXX: Uncensored","title_hi":null,"year":"2018","type":"series","imdb_rating":"4.9","image_url":"att9010756z.jpg"},{"id":41269,"slug":"a-night-to-remember","title":"A Night to Remember","title_hi":null,"year":"1958","type":"movie","imdb_rating":"7.9","image_url":"att0051994z.jpg"},{"id":41257,"slug":"fazilet-hanim-ve-kizlari","title":"Fazilet Hanim ve Kizlari","title_hi":null,"year":"2017–2018","type":"series","imdb_rating":"6.9","image_url":"att6756704z.jpg"},{"id":41242,"slug":"dreamer-inspired-by-a-true-story","title":"Dreamer: Inspired by a True Story","title_hi":null,"year":"2005","type":"movie","imdb_rating":"6.8","image_url":"att0418647z.jpg"},{"id":41240,"slug":"echo","title":"Echo","title_hi":null,"year":"2019","type":"movie","imdb_rating":"7.1","image_url":"att9296808z.jpg"},{"id":41202,"slug":"jesse-stone-thin-ice","title":"Jesse Stone: Thin Ice","title_hi":null,"year":"2009","type":"movie","imdb_rating":"7.2","image_url":"att1064884z.jpg"}],"updatedAt":"2026-03-24T12:42:20.258Z"}