{"id":33908,"slug":"main-khiladi-tu-anari","title":"Main Khiladi Tu Anari","title_hi":null,"year":"1994","type":"movie","plot":"A Bombay police officer seeks revenge when his brother is killed by a powerful underworld figure. Things get complicated when a matinee movie idol begins to tag along the policeman so he can research a movie role.","plot_hi":null,"runtime":"175 min","rated":null,"language":null,"country":"India","box_office":null,"awards":null,"imdb_id":null,"imdb_rating":"6.5","status":"published","image_url":"att0110438z.jpg","date_created":"2021-08-22T01:16:17.300Z","ratings":[{"source":"Internet Movie Database","value":"6.5/10"}],"genres":[{"id":1,"name":"Action","slug":"action"},{"id":6,"name":"Comedy","slug":"comedy"},{"id":9,"name":"Drama","slug":"drama"},{"id":20,"name":"Romance","slug":"romance"}],"cast":[{"id":116,"name":"Akshay Kumar","slug":"akshay-kumar"},{"id":2776,"name":"Saif Ali Khan","slug":"saif-ali-khan"},{"id":52622,"name":"Shilpa Shetty Kundra","slug":"shilpa-shetty-kundra"},{"id":82247,"name":"Raageshwari","slug":"raageshwari"}],"directors":[{"id":82248,"name":"Sameer Malkan","slug":"sameer-malkan"}],"writers":[{"id":11041,"name":"Sachin Bhowmick","slug":"sachin-bhowmick"},{"id":71217,"name":"Kader Khan","slug":"kader-khan"}],"recommendations":[{"id":35730,"slug":"sabse-bada-khiladi","title":"Sabse Bada Khiladi","title_hi":null,"year":"1995","type":"movie","imdb_rating":"6","image_url":"att0114317z.jpg"},{"id":35502,"slug":"mohra","title":"Mohra","title_hi":null,"year":"1994","type":"movie","imdb_rating":"6.9","image_url":"att0110546z.jpg"},{"id":34373,"slug":"garv-pride-and-honour","title":"Garv: Pride and Honour","title_hi":null,"year":"2004","type":"movie","imdb_rating":"5.5","image_url":"att0415003z.jpg"},{"id":34025,"slug":"jaani-dushman-ek-anokhi-kahani","title":"Jaani Dushman: Ek Anokhi Kahani","title_hi":null,"year":"2002","type":"movie","imdb_rating":"2.8","image_url":"att0326983z.jpg"},{"id":33690,"slug":"sangharsh","title":"Sangharsh","title_hi":null,"year":"1999","type":"movie","imdb_rating":"7.2","image_url":"att0111068z.jpg"},{"id":33001,"slug":"prithviraj","title":"Prithviraj","title_hi":null,"year":"2020","type":"movie","imdb_rating":null,"image_url":"att9637132z.jpg"},{"id":7895,"slug":"me-and-you","title":"Me and You","title_hi":null,"year":"2004","type":"movie","imdb_rating":"7","image_url":"att0378072z.jpg"},{"id":5337,"slug":"housefull-4","title":"Housefull 4","title_hi":null,"year":"2019","type":"movie","imdb_rating":"3.4","image_url":"att7721946z.jpg"},{"id":3829,"slug":"good-newwz","title":"Good Newwz","title_hi":null,"year":"2019","type":"movie","imdb_rating":"7","image_url":"att8504014z.jpg"},{"id":3824,"slug":"kal-ho-naa-ho","title":"Kal ho naa ho","title_hi":null,"year":"2003","type":"movie","imdb_rating":"8","image_url":"att0347304z.jpg"},{"id":1048,"slug":"race-2","title":"Race 2","title_hi":null,"year":"2013","type":"movie","imdb_rating":"5.3","image_url":"att1375789z.jpg"}],"updatedAt":"2026-03-24T12:41:25.347Z"}