{"id":34290,"slug":"let-there-be-victory","title":"Let There Be Victory","title_hi":null,"year":"2014","type":"movie","plot":"An ex-army officer initiates a unique idea of propagating social responsibility among ordinary people and in doing so, crosses paths with a powerful political family.","plot_hi":null,"runtime":"135 min","rated":"Not Rated","language":null,"country":"India","box_office":"$1,187,266","awards":"1 win & 5 nominations.","imdb_id":null,"imdb_rating":"5.2","status":"published","image_url":"att1188982z.jpg","date_created":"2021-08-26T00:46:03.975Z","ratings":[{"source":"Internet Movie Database","value":"5.2/10"},{"source":"Rotten Tomatoes","value":"18%"}],"genres":[{"id":1,"name":"Action","slug":"action"},{"id":9,"name":"Drama","slug":"drama"}],"cast":[{"id":49077,"name":"Salman Khan","slug":"salman-khan"},{"id":83062,"name":"Daisy Shah","slug":"daisy-shah"},{"id":210,"name":"Tabu","slug":"tabu"},{"id":7714,"name":"Danny Denzongpa","slug":"danny-denzongpa"}],"directors":[{"id":41479,"name":"Sohail Khan","slug":"sohail-khan"}],"writers":[{"id":20449,"name":"A.R. Murugadoss","slug":"a.r.-murugadoss"},{"id":81151,"name":"Dilip Shukla","slug":"dilip-shukla"}],"recommendations":[{"id":35739,"slug":"jeet","title":"Jeet","title_hi":null,"year":"1996","type":"movie","imdb_rating":"5.6","image_url":"att0116690z.jpg"},{"id":33971,"slug":"maachis","title":"Maachis","title_hi":null,"year":"1996","type":"movie","imdb_rating":"7.8","image_url":"att0116950z.jpg"},{"id":32558,"slug":"tiger-zinda-hai","title":"Tiger Zinda Hai","title_hi":null,"year":"2017","type":"movie","imdb_rating":"6","image_url":"att5956100z.jpg"},{"id":31046,"slug":"love-story","title":"Love Story","title_hi":null,"year":"1981","type":"movie","imdb_rating":"6.4","image_url":"att0234141z.jpg"},{"id":30014,"slug":"pyaar-kiya-to-darna-kya","title":"Pyaar Kiya To Darna Kya","title_hi":null,"year":"1998","type":"movie","imdb_rating":"6.7","image_url":"att0173080z.jpg"},{"id":29367,"slug":"biwi-no.-1","title":"Biwi No. 1","title_hi":null,"year":"1999","type":"movie","imdb_rating":"5.7","image_url":"att0207341z.jpg"},{"id":29250,"slug":"khamoshi-the-musical","title":"Khamoshi: The Musical","title_hi":null,"year":"1996","type":"movie","imdb_rating":"7.5","image_url":"att0116763z.jpg"},{"id":8901,"slug":"hotchpotch-again","title":"Hotchpotch Again","title_hi":null,"year":"2017","type":"movie","imdb_rating":"4.9","image_url":"att1806913z.jpg"},{"id":7105,"slug":"de-de-pyaar-de","title":"De De Pyaar De","title_hi":null,"year":"2019","type":"movie","imdb_rating":"6.6","image_url":"att8647400z.jpg"},{"id":6314,"slug":"bang-bang","title":"Bang Bang","title_hi":null,"year":"2014","type":"movie","imdb_rating":"5.5","image_url":"att2905838z.jpg"},{"id":4069,"slug":"hera-pheri","title":"Hera Pheri","title_hi":null,"year":"2000","type":"movie","imdb_rating":"8.2","image_url":"att0242519z.jpg"},{"id":3477,"slug":"bajrangi-bhaijaan","title":"Bajrangi Bhaijaan","title_hi":null,"year":"2015","type":"movie","imdb_rating":"8","image_url":"att3863552z.jpg"}],"updatedAt":"2026-03-24T12:41:06.791Z"}