{"id":34594,"slug":"saints-row","title":"Saints Row","title_hi":null,"year":"2006","type":"game","plot":"We want Saint's Row to be the next step in the evolution of open world games. It is a game that gives you a great deal of freedom: freedom to create and customize your character, freedom to...","plot_hi":null,"runtime":null,"rated":null,"language":null,"country":"USA","box_office":null,"awards":null,"imdb_id":null,"imdb_rating":"7.8","status":"published","image_url":"att0477848z.jpg","date_created":"2021-08-29T04:47:11.186Z","ratings":[{"source":"Internet Movie Database","value":"7.8/10"}],"genres":[{"id":1,"name":"Action","slug":"action"},{"id":7,"name":"Crime","slug":"crime"},{"id":25,"name":"Thriller","slug":"thriller"}],"cast":[{"id":2663,"name":"Keith David","slug":"keith-david"},{"id":4649,"name":"Michael Rapaport","slug":"michael-rapaport"},{"id":9106,"name":"Daniel Dae Kim","slug":"daniel-dae-kim"},{"id":67717,"name":"J.A.Q.","slug":"j.a.q"}],"directors":[{"id":27000,"name":"Douglas Carrigan","slug":"douglas-carrigan"}],"writers":[{"id":82896,"name":"Steve Jaros","slug":"steve-jaros"},{"id":83745,"name":"Scott Leaton","slug":"scott-leaton"},{"id":83746,"name":"Jeffrey Bielawski","slug":"jeffrey-bielawski"},{"id":83747,"name":"Jeff Bielawski","slug":"jeff-bielawski"},{"id":83748,"name":"David H. Lawrence XVII","slug":"david-h.-lawrence-xvii"},{"id":83749,"name":"Michael Schmidt","slug":"michael-schmidt"}],"recommendations":[{"id":33249,"slug":"the-chronicles-of-riddick-dark-fury","title":"The Chronicles of Riddick: Dark Fury","title_hi":null,"year":"2004","type":"movie","imdb_rating":"6.6","image_url":"att0407658z.jpg"},{"id":30057,"slug":"some-girl","title":"Some Girl","title_hi":null,"year":"1998","type":"movie","imdb_rating":"5.8","image_url":"att0125766z.jpg"},{"id":11936,"slug":"the-puppet-masters","title":"The Puppet Masters","title_hi":null,"year":"1994","type":"movie","imdb_rating":"5.9","image_url":"att0111003z.jpg"},{"id":11533,"slug":"halo-5-guardians","title":"Halo 5: Guardians","title_hi":null,"year":"2015","type":"game","imdb_rating":"7.4","image_url":"att3467114z.jpg"},{"id":10494,"slug":"pitch-black","title":"Pitch Black","title_hi":null,"year":"2000","type":"movie","imdb_rating":"7.1","image_url":"att0134847z.jpg"},{"id":7212,"slug":"tales-from-the-hood-2","title":"Tales from the Hood 2","title_hi":null,"year":"2018","type":"movie","imdb_rating":"4.4","image_url":"att8403680z.jpg"},{"id":6896,"slug":"love-jacked","title":"Love Jacked","title_hi":null,"year":"2018","type":"movie","imdb_rating":"5.8","image_url":"att4329242z.jpg"},{"id":3986,"slug":"men-at-work","title":"Men at Work","title_hi":null,"year":"1990","type":"movie","imdb_rating":"6","image_url":"att0100135z.jpg"},{"id":1271,"slug":"the-marvel-experience","title":"The Marvel Experience","title_hi":null,"year":"2014","type":"movie","imdb_rating":"5.8","image_url":"att5080076z.jpg"},{"id":800,"slug":"todd-mcfarlanes-spawn","title":"Todd McFarlane's Spawn","title_hi":null,"year":"1997","type":"movie","imdb_rating":"8.5","image_url":"att4641774z.jpg"},{"id":280,"slug":"the-princess-and-the-frog","title":"The Princess and the Frog","title_hi":null,"year":"2009","type":"movie","imdb_rating":"7.1","image_url":"att0780521z.jpg"},{"id":255,"slug":"atypical","title":"Atypical","title_hi":null,"year":"2017–","type":"series","imdb_rating":"8.3","image_url":"att6315640z.jpg"}],"updatedAt":"2026-03-24T12:40:51.990Z"}