{"id":35489,"slug":"icarus","title":"Icarus","title_hi":null,"year":"2010","type":"movie","plot":"A Soviet-trained assassin is determined to escape his double life as a hitman and as a husband-father.","plot_hi":null,"runtime":"88 min","rated":"R","language":null,"country":"Canada","box_office":null,"awards":null,"imdb_id":null,"imdb_rating":"5.1","status":"published","image_url":"att1261862z.jpg","date_created":"2021-09-07T12:30:17.774Z","ratings":[{"source":"Internet Movie Database","value":"5.1/10"}],"genres":[{"id":1,"name":"Action","slug":"action"},{"id":9,"name":"Drama","slug":"drama"},{"id":25,"name":"Thriller","slug":"thriller"}],"cast":[{"id":362,"name":"Dolph Lundgren","slug":"dolph-lundgren"},{"id":11572,"name":"Stefanie von Pfetten","slug":"stefanie-von-pfetten"},{"id":85774,"name":"Samantha Ferris","slug":"samantha-ferris"},{"id":21856,"name":"David Lewis","slug":"david-lewis"}],"directors":[{"id":362,"name":"Dolph Lundgren","slug":"dolph-lundgren"}],"writers":[{"id":22570,"name":"Raul Inglis","slug":"raul-inglis"}],"recommendations":[{"id":39188,"slug":"stash-house","title":"Stash House","title_hi":null,"year":"2012","type":"movie","imdb_rating":"4.8","image_url":"att1919090z.jpg"},{"id":37745,"slug":"deadly-secrets-by-the-lake","title":"Deadly Secrets by the Lake","title_hi":null,"year":"2017","type":"movie","imdb_rating":"5.2","image_url":"att5895374z.jpg"},{"id":34802,"slug":"command-performance","title":"Command Performance","title_hi":null,"year":"2009","type":"movie","imdb_rating":"5.6","image_url":"att1210801z.jpg"},{"id":32402,"slug":"riot","title":"Riot","title_hi":null,"year":"2015","type":"movie","imdb_rating":"5.1","image_url":"att4642044z.jpg"},{"id":31424,"slug":"the-expendables","title":"The Expendables","title_hi":null,"year":"2010","type":"movie","imdb_rating":"6.5","image_url":"att1320253z.jpg"},{"id":22180,"slug":"evangeline","title":"Evangeline","title_hi":null,"year":"2013","type":"movie","imdb_rating":"3.6","image_url":"att2649680z.jpg"},{"id":20316,"slug":"the-minion","title":"The Minion","title_hi":null,"year":"1998","type":"movie","imdb_rating":"4","image_url":"att0139465z.jpg"},{"id":14953,"slug":"retrograde","title":"Retrograde","title_hi":null,"year":"2004","type":"movie","imdb_rating":"3.2","image_url":"att0385990z.jpg"},{"id":12289,"slug":"decoys","title":"Decoys","title_hi":null,"year":"2004","type":"movie","imdb_rating":"4.6","image_url":"att0357585z.jpg"},{"id":11296,"slug":"universal-soldier-day-of-reckoning","title":"Universal Soldier: Day of Reckoning","title_hi":null,"year":"2012","type":"movie","imdb_rating":"5","image_url":"att1659343z.jpg"},{"id":9714,"slug":"while-you-were-dating","title":"While You Were Dating","title_hi":null,"year":"2017","type":"movie","imdb_rating":"6","image_url":"att6295106z.jpg"},{"id":3522,"slug":"showdown-in-little-tokyo","title":"Showdown in Little Tokyo","title_hi":null,"year":"1991","type":"movie","imdb_rating":"6.1","image_url":"att0102915z.jpg"}],"updatedAt":"2026-03-24T12:40:08.185Z"}