{"id":35577,"slug":"justice-league-gods-and-monsters-chronicles","title":"Justice League: Gods and Monsters Chronicles","title_hi":null,"year":"2015–2016","type":"series","plot":"Taking place in an alternate reality featuring their versions of Superman, Wonder Woman, and Batman.","plot_hi":null,"runtime":"6 min","rated":null,"language":null,"country":"USA","box_office":null,"awards":"1 win.","imdb_id":null,"imdb_rating":"7.7","status":"published","image_url":"att4759674z.jpg","date_created":"2021-09-08T10:30:28.469Z","ratings":[{"source":"Internet Movie Database","value":"7.7/10"}],"genres":[{"id":1,"name":"Action","slug":"action"},{"id":3,"name":"Adventure","slug":"adventure"},{"id":4,"name":"Animation","slug":"animation"}],"cast":[{"id":4116,"name":"Tara Strong","slug":"tara-strong"},{"id":11104,"name":"Josh Keaton","slug":"josh-keaton"}],"directors":[{"id":5,"name":"N/A","slug":"na"}],"writers":[{"id":1488,"name":"Bob Kane","slug":"bob-kane"}],"recommendations":[{"id":19620,"slug":"the-batman-vs.-dracula","title":"The Batman vs. Dracula","title_hi":null,"year":"2005","type":"movie","imdb_rating":"6.6","image_url":"att0472219z.jpg"},{"id":16017,"slug":"the-jimmy-timmy-power-hour","title":"The Jimmy Timmy Power Hour","title_hi":null,"year":"2004","type":"movie","imdb_rating":"6.8","image_url":"att0414177z.jpg"},{"id":15056,"slug":"batman-strange-days","title":"Batman: Strange Days","title_hi":null,"year":"2014","type":"movie","imdb_rating":"7.6","image_url":"att3643208z.jpg"},{"id":11820,"slug":"dc-super-hero-girls","title":"DC Super Hero Girls","title_hi":null,"year":"2015–","type":"series","imdb_rating":"6","image_url":"att5582302z.jpg"},{"id":9850,"slug":"a-fairly-odd-summer","title":"A Fairly Odd Summer","title_hi":null,"year":"2014","type":"movie","imdb_rating":"3.9","image_url":"att3149536z.jpg"},{"id":9549,"slug":"the-powerpuff-girls-movie","title":"The Powerpuff Girls Movie","title_hi":null,"year":"2002","type":"movie","imdb_rating":"6.6","image_url":"att0289408z.jpg"},{"id":9153,"slug":"my-little-pony-equestria-girls-rainbow-rocks","title":"My Little Pony: Equestria Girls - Rainbow Rocks","title_hi":null,"year":"2014","type":"movie","imdb_rating":"6.9","image_url":"att3529198z.jpg"},{"id":8928,"slug":"lollipop-chainsaw","title":"Lollipop Chainsaw","title_hi":null,"year":"2012","type":"game","imdb_rating":"7.8","image_url":"att2188807z.jpg"},{"id":5635,"slug":"gnome-alone","title":"Gnome Alone","title_hi":null,"year":"2017","type":"movie","imdb_rating":"5.6","image_url":"att5851786z.jpg"},{"id":3886,"slug":"ben-10","title":"Ben 10","title_hi":null,"year":"2016–","type":"series","imdb_rating":"2.5","image_url":"att6148376z.jpg"},{"id":3371,"slug":"dc-super-hero-girls","title":"DC Super Hero Girls","title_hi":null,"year":"2019–","type":"series","imdb_rating":"7.1","image_url":"att9628244z.jpg"},{"id":245,"slug":"hercules","title":"Hercules","title_hi":null,"year":"1997","type":"movie","imdb_rating":"7.3","image_url":"att0119282z.jpg"}],"updatedAt":"2026-03-24T12:40:03.868Z"}