{"id":36519,"slug":"we-own-the-night","title":"We Own the Night","title_hi":null,"year":"2007","type":"movie","plot":"A New York City nightclub manager tries to save his brother and father from Russian Mafia hitmen.","plot_hi":null,"runtime":"117 min","rated":"R","language":null,"country":"USA","box_office":"$27,600,000","awards":"1 win & 6 nominations.","imdb_id":null,"imdb_rating":"6.8","status":"published","image_url":"att0498399z.jpg","date_created":"2021-09-18T06:00:34.037Z","ratings":[{"source":"Internet Movie Database","value":"6.8/10"},{"source":"Rotten Tomatoes","value":"57%"},{"source":"Metacritic","value":"59/100"}],"genres":[{"id":7,"name":"Crime","slug":"crime"},{"id":9,"name":"Drama","slug":"drama"},{"id":25,"name":"Thriller","slug":"thriller"}],"cast":[],"directors":[{"id":1390,"name":"James Gray","slug":"james-gray"}],"writers":[{"id":1390,"name":"James Gray","slug":"james-gray"}],"recommendations":[{"id":36465,"slug":"out-of-time","title":"Out of Time","title_hi":null,"year":"2003","type":"movie","imdb_rating":"6.5","image_url":"att0313443z.jpg"},{"id":36392,"slug":"8mm","title":"8MM","title_hi":null,"year":"1999","type":"movie","imdb_rating":"6.5","image_url":"att0134273z.jpg"},{"id":25964,"slug":"the-yards","title":"The Yards","title_hi":null,"year":"2000","type":"movie","imdb_rating":"6.4","image_url":"att0138946z.jpg"},{"id":25600,"slug":"return-to-paradise","title":"Return to Paradise","title_hi":null,"year":"1998","type":"movie","imdb_rating":"6.9","image_url":"att0124595z.jpg"},{"id":20420,"slug":"children-of-the-corn-v-fields-of-terror","title":"Children of the Corn V: Fields of Terror","title_hi":null,"year":"1998","type":"movie","imdb_rating":"3.9","image_url":"att0150111z.jpg"},{"id":18609,"slug":"earthlings","title":"Earthlings","title_hi":null,"year":"2005","type":"movie","imdb_rating":"8.7","image_url":"att0358456z.jpg"},{"id":3149,"slug":"im-still-here","title":"I'm Still Here","title_hi":null,"year":"2010","type":"movie","imdb_rating":"6.2","image_url":"att1356864z.jpg"},{"id":2806,"slug":"irrational-man","title":"Irrational Man","title_hi":null,"year":"2015","type":"movie","imdb_rating":"6.6","image_url":"att3715320z.jpg"},{"id":2495,"slug":"stuck-on-you","title":"Stuck on You","title_hi":null,"year":"2003","type":"movie","imdb_rating":"5.7","image_url":"att0338466z.jpg"},{"id":1038,"slug":"ladder-49","title":"Ladder 49","title_hi":null,"year":"2004","type":"movie","imdb_rating":"6.5","image_url":"att0349710z.jpg"},{"id":361,"slug":"the-other-guys","title":"The Other Guys","title_hi":null,"year":"2010","type":"movie","imdb_rating":"6.6","image_url":"att1386588z.jpg"}],"updatedAt":"2026-03-24T12:26:33.689Z"}