{"id":37285,"slug":"f.i.s.t","title":"F.I.S.T.","title_hi":null,"year":"1978","type":"movie","plot":"A rebellious Cleveland warehouse worker rises through the ranks of a trucking industry union to become union president but his organized crime links cause his eventual downfall.","plot_hi":null,"runtime":"145 min","rated":"PG","language":null,"country":"USA","box_office":null,"awards":"1 win & 1 nomination.","imdb_id":null,"imdb_rating":"6.5","status":"published","image_url":"att0077531z.jpg","date_created":"2021-09-26T05:30:59.936Z","ratings":[{"source":"Internet Movie Database","value":"6.5/10"},{"source":"Rotten Tomatoes","value":"73%"},{"source":"Metacritic","value":"54/100"}],"genres":[{"id":7,"name":"Crime","slug":"crime"},{"id":9,"name":"Drama","slug":"drama"},{"id":25,"name":"Thriller","slug":"thriller"}],"cast":[{"id":2412,"name":"Sylvester Stallone","slug":"sylvester-stallone"},{"id":10075,"name":"Rod Steiger","slug":"rod-steiger"},{"id":5681,"name":"Peter Boyle","slug":"peter-boyle"},{"id":2384,"name":"Melinda Dillon","slug":"melinda-dillon"}],"directors":[{"id":802,"name":"Norman Jewison","slug":"norman-jewison"}],"writers":[{"id":2412,"name":"Sylvester Stallone","slug":"sylvester-stallone"},{"id":59457,"name":"Joe Eszterhas","slug":"joe-eszterhas"}],"recommendations":[{"id":40491,"slug":"hardcore","title":"Hardcore","title_hi":null,"year":"1979","type":"movie","imdb_rating":"7","image_url":"att0079271z.jpg"},{"id":39199,"slug":"dirty-hands","title":"Dirty Hands","title_hi":null,"year":"1975","type":"movie","imdb_rating":"7.1","image_url":"att0073169z.jpg"},{"id":38904,"slug":"men-of-respect","title":"Men of Respect","title_hi":null,"year":"1990","type":"movie","imdb_rating":"5.5","image_url":"att0102432z.jpg"},{"id":31837,"slug":"daylight","title":"Daylight","title_hi":null,"year":"1996","type":"movie","imdb_rating":"5.9","image_url":"att0116040z.jpg"},{"id":31744,"slug":"rambo-iii","title":"Rambo III","title_hi":null,"year":"1988","type":"movie","imdb_rating":"5.8","image_url":"att0095956z.jpg"},{"id":31666,"slug":"rocky-balboa","title":"Rocky Balboa","title_hi":null,"year":"2006","type":"movie","imdb_rating":"7.1","image_url":"att0479143z.jpg"},{"id":31326,"slug":"rambo-last-blood","title":"Rambo: Last Blood","title_hi":null,"year":"2019","type":"movie","imdb_rating":"6.2","image_url":"att1206885z.jpg"},{"id":11073,"slug":"outland","title":"Outland","title_hi":null,"year":"1981","type":"movie","imdb_rating":"6.6","image_url":"att0082869z.jpg"},{"id":4036,"slug":"the-dream-team","title":"The Dream Team","title_hi":null,"year":"1989","type":"movie","imdb_rating":"6.5","image_url":"att0097235z.jpg"},{"id":2038,"slug":"while-you-were-sleeping","title":"While You Were Sleeping","title_hi":null,"year":"1995","type":"movie","imdb_rating":"6.7","image_url":"att0114924z.jpg"},{"id":2001,"slug":"tango-cash","title":"Tango & Cash","title_hi":null,"year":"1989","type":"movie","imdb_rating":"6.4","image_url":"att0098439z.jpg"},{"id":609,"slug":"young-frankenstein","title":"Young Frankenstein","title_hi":null,"year":"1974","type":"movie","imdb_rating":"8","image_url":"att0072431z.jpg"}],"updatedAt":"2026-03-24T12:20:44.262Z"}