{"id":38346,"slug":"the-secret-four","title":"The Secret Four","title_hi":null,"year":"1939","type":"movie","plot":"The Four Men of the title are British WWI veterans who decide to work secretly against enemies of the country. They aren't above a bit of murder or sabotage to serve their ends, but they ...","plot_hi":null,"runtime":"85 min","rated":"APPROVED","language":null,"country":"UK","box_office":null,"awards":null,"imdb_id":null,"imdb_rating":"6.5","status":"published","image_url":"att0033031z.jpg","date_created":"2021-10-07T06:46:09.534Z","ratings":[{"source":"Internet Movie Database","value":"6.5/10"}],"genres":[{"id":9,"name":"Drama","slug":"drama"},{"id":25,"name":"Thriller","slug":"thriller"}],"cast":[{"id":8674,"name":"Hugh Sinclair","slug":"hugh-sinclair"},{"id":68906,"name":"Griffith Jones","slug":"griffith-jones"},{"id":23870,"name":"Francis L. Sullivan","slug":"francis-l.-sullivan"},{"id":16177,"name":"Frank Lawton","slug":"frank-lawton"}],"directors":[{"id":44237,"name":"Walter Forde","slug":"walter-forde"}],"writers":[{"id":4541,"name":"Edgar Wallace","slug":"edgar-wallace"},{"id":23873,"name":"Roland Pertwee","slug":"roland-pertwee"},{"id":37880,"name":"Angus MacPhail","slug":"angus-macphail"},{"id":70199,"name":"Sergei Nolbandov","slug":"sergei-nolbandov"}],"recommendations":[{"id":41275,"slug":"oliver-twist","title":"Oliver Twist","title_hi":null,"year":"1948","type":"movie","imdb_rating":"7.8","image_url":"att0040662z.jpg"},{"id":38347,"slug":"lady-from-lisbon","title":"Lady from Lisbon","title_hi":null,"year":"1942","type":"movie","imdb_rating":"6.1","image_url":"att0029105z.jpg"},{"id":28304,"slug":"miranda","title":"Miranda","title_hi":null,"year":"1948","type":"movie","imdb_rating":"6.9","image_url":"att0040597z.jpg"},{"id":15665,"slug":"the-invisible-ray","title":"The Invisible Ray","title_hi":null,"year":"1936","type":"movie","imdb_rating":"6.6","image_url":"att0027800z.jpg"},{"id":15204,"slug":"non-stop-new-york","title":"Non-Stop New York","title_hi":null,"year":"1937","type":"movie","imdb_rating":"6.9","image_url":"att0029319z.jpg"},{"id":13331,"slug":"the-devil-doll","title":"The Devil-Doll","title_hi":null,"year":"1936","type":"movie","imdb_rating":"7","image_url":"att0027521z.jpg"},{"id":1168,"slug":"corridor-of-mirrors","title":"Corridor of Mirrors","title_hi":null,"year":"1948","type":"movie","imdb_rating":"6.6","image_url":"att0040246z.jpg"}],"updatedAt":"2026-03-24T12:12:41.183Z"}