{"id":39973,"slug":"the-miseducation-of-cameron-post","title":"The Miseducation of Cameron Post","title_hi":null,"year":"2018","type":"movie","plot":"In 1993, a teenage girl is forced into a gay conversion therapy center by her conservative guardians.","plot_hi":null,"runtime":"91 min","rated":"Not Rated","language":null,"country":"USA, UK","box_office":null,"awards":"5 wins & 14 nominations.","imdb_id":null,"imdb_rating":"6.6","status":"published","image_url":"att6257174z.jpg","date_created":"2021-10-24T05:31:40.280Z","ratings":[{"source":"Internet Movie Database","value":"6.6/10"},{"source":"Rotten Tomatoes","value":"86%"},{"source":"Metacritic","value":"69/100"}],"genres":[{"id":9,"name":"Drama","slug":"drama"}],"cast":[{"id":2790,"name":"Chloë Grace Moretz","slug":"chloe-grace-moretz"},{"id":94198,"name":"Steven Hauck","slug":"steven-hauck"},{"id":48179,"name":"Quinn Shephard","slug":"quinn-shephard"},{"id":94199,"name":"Kerry Butler","slug":"kerry-butler"}],"directors":[{"id":35666,"name":"Desiree Akhavan","slug":"desiree-akhavan"}],"writers":[{"id":35666,"name":"Desiree Akhavan","slug":"desiree-akhavan"},{"id":94200,"name":"Cecilia Frugiuele","slug":"cecilia-frugiuele"},{"id":94201,"name":"Emily M. Danforth","slug":"emily-m.-danforth"}],"recommendations":[{"id":41243,"slug":"blame","title":"Blame","title_hi":null,"year":"2017","type":"movie","imdb_rating":"5.8","image_url":"att4607722z.jpg"},{"id":40607,"slug":"november-criminals","title":"November Criminals","title_hi":null,"year":"2017","type":"movie","imdb_rating":"5.3","image_url":"att3266284z.jpg"},{"id":39919,"slug":"brain-on-fire","title":"Brain on Fire","title_hi":null,"year":"2016","type":"movie","imdb_rating":"6.6","image_url":"att3704700z.jpg"},{"id":36317,"slug":"greta","title":"Greta","title_hi":null,"year":"2018","type":"movie","imdb_rating":"6","image_url":"att2639336z.jpg"},{"id":20330,"slug":"room-6","title":"Room 6","title_hi":null,"year":"2006","type":"movie","imdb_rating":"4.2","image_url":"att0451187z.jpg"},{"id":18206,"slug":"let-me-in","title":"Let Me In","title_hi":null,"year":"2010","type":"movie","imdb_rating":"7.1","image_url":"att1228987z.jpg"},{"id":10483,"slug":"the-5th-wave","title":"The 5th Wave","title_hi":null,"year":"2016","type":"movie","imdb_rating":"5.2","image_url":"att2304933z.jpg"},{"id":5017,"slug":"hick","title":"Hick","title_hi":null,"year":"2011","type":"movie","imdb_rating":"5.6","image_url":"att1205558z.jpg"},{"id":1773,"slug":"kick-ass-2","title":"Kick-Ass 2","title_hi":null,"year":"2013","type":"movie","imdb_rating":"6.5","image_url":"att1650554z.jpg"},{"id":461,"slug":"500-days-of-summer","title":"500 Days of Summer","title_hi":null,"year":"2009","type":"movie","imdb_rating":"7.7","image_url":"att1022603z.jpg"},{"id":417,"slug":"the-addams-family","title":"The Addams Family","title_hi":null,"year":"2019","type":"movie","imdb_rating":"5.8","image_url":"att1620981z.jpg"},{"id":307,"slug":"red-shoes-and-the-seven-dwarfs","title":"Red Shoes and the Seven Dwarfs","title_hi":null,"year":"2019","type":"movie","imdb_rating":"6.3","image_url":"att4429160z.jpg"}],"updatedAt":"2026-03-24T12:00:15.588Z"}