{"id":40400,"slug":"the-naked-director","title":"The Naked Director","title_hi":null,"year":"2019–","type":"series","plot":"Follows the story of Toru Muranishi's unusual and dramatic life filled with big ambitions as well as spectacular setbacks in his attempt to turn Japan's porn industry on its head","plot_hi":null,"runtime":"48 min","rated":"TV-MA","language":null,"country":"Japan","box_office":null,"awards":null,"imdb_id":null,"imdb_rating":"7.9","status":"published","image_url":"att10477528z.jpg","date_created":"2021-10-28T16:15:39.278Z","ratings":[{"source":"Internet Movie Database","value":"7.9/10"}],"genres":[{"id":5,"name":"Biography","slug":"biography"},{"id":9,"name":"Drama","slug":"drama"}],"cast":[{"id":9649,"name":"Takayuki Yamada","slug":"takayuki-yamada"},{"id":3614,"name":"Shinnosuke Mitsushima","slug":"shinnosuke-mitsushima"},{"id":94974,"name":"Misato Morita","slug":"misato-morita"},{"id":39164,"name":"Tetsuji Tamayama","slug":"tetsuji-tamayama"}],"directors":[{"id":5,"name":"N/A","slug":"na"}],"writers":[{"id":5,"name":"N/A","slug":"na"}],"recommendations":[{"id":33055,"slug":"crows-zero","title":"Crows Zero","title_hi":null,"year":"2007","type":"movie","imdb_rating":"7.1","image_url":"att1016290z.jpg"},{"id":19781,"slug":"lesson-of-the-evil","title":"Lesson of the Evil","title_hi":null,"year":"2012","type":"movie","imdb_rating":"6.6","image_url":"att2294473z.jpg"},{"id":18795,"slug":"the-forest-of-love","title":"The Forest of Love","title_hi":null,"year":"2019","type":"movie","imdb_rating":"6.4","image_url":"att10589914z.jpg"},{"id":17332,"slug":"nobunaga-concerto","title":"Nobunaga Concerto","title_hi":null,"year":"2014–","type":"series","imdb_rating":"8","image_url":"att3721064z.jpg"},{"id":15799,"slug":"napping-princess","title":"Napping Princess","title_hi":null,"year":"2017","type":"movie","imdb_rating":"6.3","image_url":"att5731132z.jpg"},{"id":11889,"slug":"terra-formars","title":"Terra Formars","title_hi":null,"year":"2016","type":"movie","imdb_rating":"4.7","image_url":"att4433646z.jpg"},{"id":10646,"slug":"erased","title":"Erased","title_hi":null,"year":"2016","type":"series","imdb_rating":"8.5","image_url":"att5249462z.jpg"},{"id":9813,"slug":"samurai-gourmet","title":"Samurai Gourmet","title_hi":null,"year":"2017","type":"series","imdb_rating":"8.2","image_url":"att6304676z.jpg"},{"id":9115,"slug":"lupin-the-3rd","title":"Lupin the 3rd","title_hi":null,"year":"2014","type":"movie","imdb_rating":"5.5","image_url":"att0862748z.jpg"},{"id":7264,"slug":"gintama-live-action-the-movie","title":"Gintama Live Action the Movie","title_hi":null,"year":"2017","type":"movie","imdb_rating":"6.2","image_url":"att5805470z.jpg"},{"id":2755,"slug":"the-cat-returns","title":"The Cat Returns","title_hi":null,"year":"2002","type":"movie","imdb_rating":"7.2","image_url":"att0347618z.jpg"}],"updatedAt":"2026-03-24T11:56:58.881Z"}