{"id":6487,"slug":"utopia","title":"Utopia","title_hi":null,"year":"2014–","type":"series","plot":"Comedy set inside the offices of the \"Nation Building Authority\", a newly created government organization responsible for overseeing major infrastructure projects.","plot_hi":null,"runtime":"27 min","rated":null,"language":null,"country":"Australia","box_office":null,"awards":"4 wins & 10 nominations.","imdb_id":null,"imdb_rating":"8.3","status":"published","image_url":"att3163562z.jpg","date_created":"2020-11-06T19:46:20.152Z","ratings":[{"source":"Internet Movie Database","value":"8.3/10"}],"genres":[{"id":6,"name":"Comedy","slug":"comedy"}],"cast":[{"id":74224,"name":"Rob Sitch","slug":"rob-sitch"},{"id":73042,"name":"Celia Pacquola","slug":"celia-pacquola"},{"id":113025,"name":"Dave Lawson","slug":"dave-lawson"},{"id":113026,"name":"Emma-Louise Wilson","slug":"emma-louise-wilson"}],"directors":[{"id":5,"name":"N/A","slug":"na"}],"writers":[{"id":74224,"name":"Rob Sitch","slug":"rob-sitch"},{"id":74225,"name":"Santo Cilauro","slug":"santo-cilauro"},{"id":74226,"name":"Tom Gleisner","slug":"tom-gleisner"}],"recommendations":[{"id":40804,"slug":"the-beautiful-lie","title":"The Beautiful Lie","title_hi":null,"year":"2015–","type":"series","imdb_rating":"7.3","image_url":"att4600360z.jpg"},{"id":6474,"slug":"the-breaker-upperers","title":"The Breaker Upperers","title_hi":null,"year":"2018","type":"movie","imdb_rating":"5.9","image_url":"att6728096z.jpg"},{"id":2985,"slug":"rosehaven","title":"Rosehaven","title_hi":null,"year":"2016–","type":"series","imdb_rating":"7.8","image_url":"att5226698z.jpg"},{"id":38961,"slug":"slither","title":"Slither","title_hi":null,"year":"1973","type":"movie","imdb_rating":"6.2","image_url":"att0069282z.jpg"},{"id":38954,"slug":"the-39-steps","title":"The 39 Steps","title_hi":null,"year":"1959","type":"movie","imdb_rating":"6.6","image_url":"att0053354z.jpg"},{"id":38538,"slug":"bad-eggs","title":"Bad Eggs","title_hi":null,"year":"2003","type":"movie","imdb_rating":"6.4","image_url":"att0312409z.jpg"},{"id":38517,"slug":"for-the-weekend","title":"For the Weekend","title_hi":null,"year":"2020","type":"movie","imdb_rating":"4.2","image_url":"att8089234z.jpg"},{"id":38047,"slug":"ulidavaru-kandanthe","title":"Ulidavaru Kandanthe","title_hi":null,"year":"2014","type":"movie","imdb_rating":"8.7","image_url":"att3394420z.jpg"},{"id":35721,"slug":"the-lord-of-the-g-strings-the-femaleship-of-the-string","title":"The Lord of the G-Strings: The Femaleship of the String","title_hi":null,"year":"2003","type":"movie","imdb_rating":"3.7","image_url":"att0323108z.jpg"},{"id":35719,"slug":"bad-black","title":"Bad Black","title_hi":null,"year":"2016","type":"movie","imdb_rating":"7.4","image_url":"att6044414z.jpg"},{"id":35702,"slug":"yamadonga","title":"Yamadonga","title_hi":null,"year":"2007","type":"movie","imdb_rating":"7.4","image_url":"att0924317z.jpg"}],"updatedAt":"2026-03-24T13:03:36.536Z"}