{"id":9576,"slug":"crazy-kind-of-love","title":"Crazy Kind of Love","title_hi":null,"year":"2013","type":"movie","plot":"A broken family finds their relationships to one another changed by a new arrival in the household.","plot_hi":null,"runtime":"100 min","rated":"R","language":null,"country":"USA","box_office":null,"awards":null,"imdb_id":null,"imdb_rating":"5.8","status":"published","image_url":"att1946310z.jpg","date_created":"2020-12-09T00:16:27.627Z","ratings":[{"source":"Internet Movie Database","value":"5.8/10"}],"genres":[{"id":6,"name":"Comedy","slug":"comedy"},{"id":9,"name":"Drama","slug":"drama"},{"id":20,"name":"Romance","slug":"romance"}],"cast":[{"id":2263,"name":"Virginia Madsen","slug":"virginia-madsen"},{"id":55855,"name":"Graham Rogers","slug":"graham-rogers"},{"id":2250,"name":"Amanda Crew","slug":"amanda-crew"},{"id":4182,"name":"Zach Gilford","slug":"zach-gilford"}],"directors":[{"id":118308,"name":"Sarah Siegel-Magness","slug":"sarah-siegel-magness"}],"writers":[{"id":32990,"name":"Karen McCullah","slug":"karen-mccullah"},{"id":118309,"name":"April Stevens","slug":"april-stevens"}],"recommendations":[{"id":38497,"slug":"a-crooked-somebody","title":"A Crooked Somebody","title_hi":null,"year":"2017","type":"movie","imdb_rating":"6.2","image_url":"att5922124z.jpg"},{"id":37498,"slug":"smith","title":"Smith","title_hi":null,"year":"2006–2007","type":"series","imdb_rating":"7.9","image_url":"att0805667z.jpg"},{"id":36673,"slug":"firewall","title":"Firewall","title_hi":null,"year":"2006","type":"movie","imdb_rating":"5.8","image_url":"att0408345z.jpg"},{"id":36511,"slug":"the-number-23","title":"The Number 23","title_hi":null,"year":"2007","type":"movie","imdb_rating":"6.4","image_url":"att0481369z.jpg"},{"id":29889,"slug":"the-hearst-and-davies-affair","title":"The Hearst and Davies Affair","title_hi":null,"year":"1985","type":"movie","imdb_rating":"6.1","image_url":"att0089260z.jpg"},{"id":28769,"slug":"long-gone","title":"Long Gone","title_hi":null,"year":"1987","type":"movie","imdb_rating":"7.8","image_url":"att0093433z.jpg"},{"id":19061,"slug":"dead-rising-watchtower","title":"Dead Rising: Watchtower","title_hi":null,"year":"2015","type":"movie","imdb_rating":"5.2","image_url":"att3816458z.jpg"},{"id":18607,"slug":"the-haunting-in-connecticut","title":"The Haunting in Connecticut","title_hi":null,"year":"2009","type":"movie","imdb_rating":"5.9","image_url":"att0492044z.jpg"},{"id":11158,"slug":"highlander-ii-the-quickening","title":"Highlander II: The Quickening","title_hi":null,"year":"1991","type":"movie","imdb_rating":"4.3","image_url":"att0102034z.jpg"},{"id":10766,"slug":"the-purge-anarchy","title":"The Purge: Anarchy","title_hi":null,"year":"2014","type":"movie","imdb_rating":"6.4","image_url":"att2975578z.jpg"},{"id":8138,"slug":"creator","title":"Creator","title_hi":null,"year":"1985","type":"movie","imdb_rating":"6.2","image_url":"att0088960z.jpg"},{"id":1639,"slug":"sex-drive","title":"Sex Drive","title_hi":null,"year":"2008","type":"movie","imdb_rating":"6.5","image_url":"att1135985z.jpg"}],"updatedAt":"2026-03-24T13:01:06.849Z"}