{"page":717,"total":47375,"pageSize":24,"sort":"rating","movies":[{"id":6330,"slug":"eating-raoul","title":"Eating Raoul","title_hi":null,"year":"1982","type":"movie","imdb_rating":"6.8","image_url":"att0083869z.jpg"},{"id":6315,"slug":"defendor","title":"Defendor","title_hi":null,"year":"2009","type":"movie","imdb_rating":"6.8","image_url":"att1303828z.jpg"},{"id":6313,"slug":"happythankyoumoreplease","title":"Happythankyoumoreplease","title_hi":null,"year":"2010","type":"movie","imdb_rating":"6.8","image_url":"att1481572z.jpg"},{"id":6300,"slug":"indiscreet","title":"Indiscreet","title_hi":null,"year":"1958","type":"movie","imdb_rating":"6.8","image_url":"att0051773z.jpg"},{"id":6226,"slug":"family-feud","title":"Family Feud","title_hi":null,"year":"1999–","type":"series","imdb_rating":"6.8","image_url":"att0177440z.jpg"},{"id":6145,"slug":"chico-and-the-man","title":"Chico and the Man","title_hi":null,"year":"1974–1978","type":"series","imdb_rating":"6.8","image_url":"att0070975z.jpg"},{"id":6072,"slug":"cyberchase","title":"Cyberchase","title_hi":null,"year":"2002–","type":"series","imdb_rating":"6.8","image_url":"att0309141z.jpg"},{"id":6065,"slug":"i-wanna-hold-your-hand","title":"I Wanna Hold Your Hand","title_hi":null,"year":"1978","type":"movie","imdb_rating":"6.8","image_url":"att0077714z.jpg"},{"id":6059,"slug":"2-days-in-paris","title":"2 Days in Paris","title_hi":null,"year":"2007","type":"movie","imdb_rating":"6.8","image_url":"att0841044z.jpg"},{"id":6054,"slug":"phir-hera-pheri","title":"Phir Hera Pheri","title_hi":null,"year":"2006","type":"movie","imdb_rating":"6.8","image_url":"att0419058z.jpg"},{"id":5998,"slug":"amen","title":"Amen","title_hi":null,"year":"1986–1991","type":"series","imdb_rating":"6.8","image_url":"att0090395z.jpg"},{"id":5989,"slug":"fahim","title":"Fahim","title_hi":null,"year":"2019","type":"movie","imdb_rating":"6.8","image_url":"att4693588z.jpg"},{"id":5959,"slug":"fallet","title":"Fallet","title_hi":null,"year":"2017–","type":"series","imdb_rating":"6.8","image_url":"att6433844z.jpg"},{"id":5948,"slug":"dragon-ball-gt","title":"Dragon Ball GT","title_hi":null,"year":"1996–2002","type":"series","imdb_rating":"6.8","image_url":"att0139774z.jpg"},{"id":5930,"slug":"mr.-bean-the-animated-series","title":"Mr. Bean: The Animated Series","title_hi":null,"year":"2002–2019","type":"series","imdb_rating":"6.8","image_url":"att0280277z.jpg"},{"id":5880,"slug":"medcezir","title":"Medcezir","title_hi":null,"year":"2013–2015","type":"series","imdb_rating":"6.8","image_url":"att3150586z.jpg"},{"id":5875,"slug":"inspector-gadget","title":"Inspector Gadget","title_hi":null,"year":"1983–1986","type":"series","imdb_rating":"6.8","image_url":"att0085033z.jpg"},{"id":5777,"slug":"the-upside-of-anger","title":"The Upside of Anger","title_hi":null,"year":"2005","type":"movie","imdb_rating":"6.8","image_url":"att0365885z.jpg"},{"id":5727,"slug":"quick-change","title":"Quick Change","title_hi":null,"year":"1990","type":"movie","imdb_rating":"6.8","image_url":"att0100449z.jpg"},{"id":5701,"slug":"the-neighbors","title":"The Neighbors","title_hi":null,"year":"2012–2014","type":"series","imdb_rating":"6.8","image_url":"att2182229z.jpg"},{"id":5699,"slug":"beavis-and-butt-head-do-america","title":"Beavis and Butt-Head Do America","title_hi":null,"year":"1996","type":"movie","imdb_rating":"6.8","image_url":"att0115641z.jpg"},{"id":5663,"slug":"the-importance-of-being-earnest","title":"The Importance of Being Earnest","title_hi":null,"year":"2002","type":"movie","imdb_rating":"6.8","image_url":"att0278500z.jpg"},{"id":5618,"slug":"comet","title":"Comet","title_hi":null,"year":"2014","type":"movie","imdb_rating":"6.8","image_url":"att2965412z.jpg"},{"id":5555,"slug":"grays-anatomy","title":"Gray's Anatomy","title_hi":null,"year":"1996","type":"movie","imdb_rating":"6.8","image_url":"att0116447z.jpg"}],"updatedAt":"2026-03-24T10:48:41.013Z"}