{"page":1033,"total":47375,"pageSize":24,"sort":"latest","movies":[{"id":22609,"slug":"this-is-our-home","title":"This Is Our Home","title_hi":null,"year":"2019","type":"movie","imdb_rating":"3.4","image_url":"att8179944z.jpg"},{"id":22608,"slug":"dreamworks-shreks-swamp-stories","title":"DreamWorks Shrek's Swamp Stories","title_hi":null,"year":"2010","type":"series","imdb_rating":"7","image_url":"att6950338z.jpg"},{"id":22607,"slug":"invocation-of-my-demon-brother","title":"Invocation of My Demon Brother","title_hi":null,"year":"1969","type":"movie","imdb_rating":"6.6","image_url":"att0064493z.jpg"},{"id":22606,"slug":"the-pantry-ghost-documentary","title":"The Pantry Ghost Documentary","title_hi":null,"year":"2013","type":"movie","imdb_rating":"5.4","image_url":"att4181558z.jpg"},{"id":22605,"slug":"red-nights","title":"Red Nights","title_hi":null,"year":"2010","type":"movie","imdb_rating":"5.5","image_url":"att1401668z.jpg"},{"id":22604,"slug":"chaw","title":"Chaw","title_hi":null,"year":"2009","type":"movie","imdb_rating":"5.7","image_url":"att1198396z.jpg"},{"id":22603,"slug":"killers","title":"Killers","title_hi":null,"year":"1996","type":"movie","imdb_rating":"5.6","image_url":"att0256858z.jpg"},{"id":22602,"slug":"beautiful-girl-hunter","title":"Beautiful Girl Hunter","title_hi":null,"year":"1979","type":"movie","imdb_rating":"6.1","image_url":"att0225458z.jpg"},{"id":22601,"slug":"under-your-bed","title":"Under Your Bed","title_hi":null,"year":"2019","type":"movie","imdb_rating":"6","image_url":"att9855728z.jpg"},{"id":22600,"slug":"snuff-killer-la-morte-in-diretta","title":"Snuff killer - La morte in diretta","title_hi":null,"year":"2003","type":"movie","imdb_rating":"3.6","image_url":"att0400837z.jpg"},{"id":22599,"slug":"i-bury-the-living","title":"I Bury the Living","title_hi":null,"year":"1958","type":"movie","imdb_rating":"6.3","image_url":"att0051755z.jpg"},{"id":22598,"slug":"shiver","title":"Shiver","title_hi":null,"year":"2012","type":"movie","imdb_rating":"4.4","image_url":"att1800734z.jpg"},{"id":22597,"slug":"kara-no-kyoukai-the-garden-of-sinners-overlooking-view","title":"Kara no Kyoukai: The Garden of Sinners - Overlooking View","title_hi":null,"year":"2007","type":"movie","imdb_rating":"7","image_url":"att1155650z.jpg"},{"id":22596,"slug":"bhoot-returns","title":"Bhoot Returns","title_hi":null,"year":"2012","type":"movie","imdb_rating":"2.5","image_url":"att2406636z.jpg"},{"id":22595,"slug":"zomboobies","title":"Zomboobies!","title_hi":null,"year":"2014","type":"movie","imdb_rating":"5.8","image_url":"att2366043z.jpg"},{"id":22594,"slug":"american-grindhouse","title":"American Grindhouse","title_hi":null,"year":"2010","type":"movie","imdb_rating":"7.1","image_url":"att1307861z.jpg"},{"id":22593,"slug":"bestseller","title":"Bestseller","title_hi":null,"year":"2010","type":"movie","imdb_rating":"6.2","image_url":"att1655617z.jpg"},{"id":22592,"slug":"7-from-etheria","title":"7 from Etheria","title_hi":null,"year":"2017","type":"movie","imdb_rating":"5.1","image_url":"att7073518z.jpg"},{"id":22591,"slug":"lilith","title":"Lilith","title_hi":null,"year":"2018","type":"movie","imdb_rating":"3.7","image_url":"att6922804z.jpg"},{"id":22590,"slug":"the-thing-that-couldnt-die","title":"The Thing That Couldn't Die","title_hi":null,"year":"1958","type":"movie","imdb_rating":"3.7","image_url":"att0052289z.jpg"},{"id":22589,"slug":"cookie","title":"Cookie","title_hi":null,"year":"2020","type":"movie","imdb_rating":"9.9","image_url":"att11743900z.jpg"},{"id":22588,"slug":"old-37","title":"Old 37","title_hi":null,"year":"2015","type":"movie","imdb_rating":"3.9","image_url":"att1600429z.jpg"},{"id":22587,"slug":"enter-the-devil","title":"Enter the Devil","title_hi":null,"year":"1974","type":"movie","imdb_rating":"4.6","image_url":"att0072147z.jpg"},{"id":22586,"slug":"insecticidal","title":"Insecticidal","title_hi":null,"year":"2005","type":"movie","imdb_rating":"3.2","image_url":"att0451085z.jpg"}],"updatedAt":"2026-03-24T10:30:52.784Z"}